[
  {
    "deviceId": "adt7410",
    "deviceDashboardUrl": "https://chirimen-device-dashboard.web.app/devices/adt7410",
    "examples": [
      {
        "platform": "legacy-gc-i2c",
        "localPath": "examples/devices/adt7410/platforms/legacy-gc-i2c",
        "upstreamRepository": "chirimen-oh/chirimen",
        "upstreamPath": "gc/i2c/i2c-ADT7410",
        "status": "archive",
        "verified": false
      },
      {
        "platform": "microbit-driver",
        "localPath": "examples/devices/adt7410/platforms/microbit-driver",
        "upstreamRepository": "chirimen-oh/chirimen-drivers",
        "upstreamPath": "microbit-examples/adt7410",
        "status": "legacy",
        "verified": false
      },
      {
        "platform": "node",
        "localPath": "examples/devices/adt7410/platforms/node",
        "upstreamRepository": "chirimen-oh/chirimen-drivers",
        "upstreamPath": "node-examples/adt7410",
        "status": "legacy",
        "verified": false
      },
      {
        "platform": "pizero-esm",
        "localPath": "examples/devices/adt7410/platforms/pizero-esm",
        "upstreamRepository": "chirimen-oh/chirimen.org",
        "upstreamPath": "pizero/src/esm-examples/adt7410",
        "status": "primary",
        "verified": false
      },
      {
        "platform": "raspi-node",
        "localPath": "examples/devices/adt7410/platforms/raspi-node",
        "upstreamRepository": "chirimen-oh/chirimen-drivers",
        "upstreamPath": "raspi-examples/adt7410",
        "status": "legacy",
        "verified": false
      }
    ]
  },
  {
    "deviceId": "bme280",
    "deviceDashboardUrl": "https://chirimen-device-dashboard.web.app/devices/bme280",
    "examples": [
      {
        "platform": "node",
        "localPath": "examples/devices/bme280/platforms/node",
        "upstreamRepository": "chirimen-oh/chirimen-drivers",
        "upstreamPath": "node-examples/bme280",
        "status": "legacy",
        "verified": false
      },
      {
        "platform": "pizero-esm",
        "localPath": "examples/devices/bme280/platforms/pizero-esm",
        "upstreamRepository": "chirimen-oh/chirimen.org",
        "upstreamPath": "pizero/src/esm-examples/bme280",
        "status": "primary",
        "verified": false
      },
      {
        "platform": "raspi-node",
        "localPath": "examples/devices/bme280/platforms/raspi-node",
        "upstreamRepository": "chirimen-oh/chirimen-drivers",
        "upstreamPath": "raspi-examples/bme280",
        "status": "legacy",
        "verified": false
      }
    ]
  },
  {
    "deviceId": "pca9685",
    "deviceDashboardUrl": "https://chirimen-device-dashboard.web.app/devices/pca9685",
    "examples": [
      {
        "platform": "legacy-gc-i2c",
        "localPath": "examples/devices/pca9685/platforms/legacy-gc-i2c",
        "upstreamRepository": "chirimen-oh/chirimen",
        "upstreamPath": "gc/i2c/i2c-PCA9685",
        "status": "archive",
        "verified": false
      },
      {
        "platform": "node",
        "localPath": "examples/devices/pca9685/platforms/node",
        "upstreamRepository": "chirimen-oh/chirimen-drivers",
        "upstreamPath": "node-examples/pca9685",
        "status": "legacy",
        "verified": false
      },
      {
        "platform": "pizero-esm",
        "localPath": "examples/devices/pca9685/platforms/pizero-esm",
        "upstreamRepository": "chirimen-oh/chirimen.org",
        "upstreamPath": "pizero/src/esm-examples/pca9685",
        "status": "primary",
        "verified": false
      },
      {
        "platform": "raspi-node",
        "localPath": "examples/devices/pca9685/platforms/raspi-node",
        "upstreamRepository": "chirimen-oh/chirimen-drivers",
        "upstreamPath": "raspi-examples/pca9685",
        "status": "legacy",
        "verified": false
      }
    ]
  }
]
